wraipperz/__init__.py
wraipperz/py.typed
wraipperz/api/__init__.py
wraipperz/api/asr.py
wraipperz/api/llm.py
wraipperz/api/messages.py
wraipperz/api/tts.py
wraipperz/api/video_gen.py
wraipperz/parsing/__init__.py
wraipperz/parsing/yaml_utils.py
wraipperz-0.1.44.dist-info/METADATA
wraipperz-0.1.44.dist-info/WHEEL
wraipperz-0.1.44.dist-info/RECORD
