Metadata-Version: 2.4
Name: wraipperz
Version: 0.1.44
Summary: Simple wrappers for various AI APIs including LLMs, ASR, and TTS
Project-URL: Homepage, https://github.com/Ahaeflig/wraipperz
Project-URL: Bug Tracker, https://github.com/Ahaeflig/wraipperz/issues
Author-email: Adan Häfliger <adan.haefliger@gmail.com>
License: MIT
Keywords: ai,anthropic,asr,google,llm,openai,tts,wrapper
Classifier: Development Status :: 4 - Beta
Classifier: Intended Audience :: Developers
Classifier: License :: OSI Approved :: MIT License
Classifier: Programming Language :: Python :: 3
Classifier: Programming Language :: Python :: 3.10
Classifier: Topic :: Software Development :: Libraries :: Python Modules
Requires-Python: >=3.10
Requires-Dist: anthropic>=0.49.0
Requires-Dist: boto3>=1.38.31
Requires-Dist: cartesia==2.0.0
Requires-Dist: deepgram-sdk>=3.10.1
Requires-Dist: fal-client>=0.5.9
Requires-Dist: google-genai>=1.5.0
Requires-Dist: google-generativeai>=0.8.4
Requires-Dist: openai>=1.66.3
Requires-Dist: pillow>=11.1.0
Requires-Dist: python-dotenv>=1.0.1
Requires-Dist: soundfile>=0.13.1
Requires-Dist: tenacity>=9.0.0
Requires-Dist: websocket-client>=1.8.0
Requires-Dist: websockets>=14.2
